[
  {
    "id": "landing_light_led_driver_hours",
    "system": "lighting",
    "subsystem": "Landing Light",
    "displayName": "Landing Light LED Driver Hours",
    "anpTerm": "Landing Light LED Driver Operating Hours",
    "unit": "hours",
    "nominalNew": 0,
    "serviceLimit": 50000,
    "failureValue": 80000,
    "direction": "increasing",
    "drivers": ["master_battery"],
    "couples": [],
    "manifestsAs": ["landing_light_dim", "landing_light_out"],
    "inspectionMethod": "Visual brightness test; measure lumens if available",
    "tboRelevance": "secondary",
    "notes": "LED dims to 70% lumens at 50000 h; total failure by 80000 h."
  },
  {
    "id": "taxi_light_led_driver_hours",
    "system": "lighting",
    "subsystem": "Taxi Light",
    "displayName": "Taxi Light LED Driver Hours",
    "anpTerm": "Taxi Light LED Driver Operating Hours",
    "unit": "hours",
    "nominalNew": 0,
    "serviceLimit": 50000,
    "failureValue": 80000,
    "direction": "increasing",
    "drivers": ["master_battery"],
    "couples": [],
    "manifestsAs": ["taxi_light_dim", "taxi_light_out"],
    "inspectionMethod": "Visual brightness test during daytime taxi",
    "tboRelevance": "secondary",
    "notes": "LED dims to 70% lumens at 50000 h; total failure by 80000 h."
  },
  {
    "id": "position_light_red_left_wing_hours",
    "system": "lighting",
    "subsystem": "Position Lights",
    "displayName": "Position Light Bulb Red (Left Wing Tip) Hours",
    "anpTerm": "Position Light Bulb Red Left Operating Hours",
    "unit": "hours",
    "nominalNew": 0,
    "serviceLimit": 1000,
    "failureValue": 1500,
    "direction": "increasing",
    "drivers": ["master_battery"],
    "couples": [],
    "manifestsAs": ["position_light_red_out"],
    "inspectionMethod": "Visual check during preflight; test during night flight",
    "tboRelevance": "primary",
    "notes": "Filament lamp 1000 h MTBF; must function for night ops."
  },
  {
    "id": "position_light_green_right_wing_hours",
    "system": "lighting",
    "subsystem": "Position Lights",
    "displayName": "Position Light Bulb Green (Right Wing Tip) Hours",
    "anpTerm": "Position Light Bulb Green Right Operating Hours",
    "unit": "hours",
    "nominalNew": 0,
    "serviceLimit": 1000,
    "failureValue": 1500,
    "direction": "increasing",
    "drivers": ["master_battery"],
    "couples": [],
    "manifestsAs": ["position_light_green_out"],
    "inspectionMethod": "Visual check during preflight; test during night flight",
    "tboRelevance": "primary",
    "notes": "Filament lamp 1000 h MTBF; required for night operations."
  },
  {
    "id": "position_light_white_tail_hours",
    "system": "lighting",
    "subsystem": "Position Lights",
    "displayName": "Position Light Bulb White (Tail) Hours",
    "anpTerm": "Position Light Bulb White Tail Operating Hours",
    "unit": "hours",
    "nominalNew": 0,
    "serviceLimit": 1000,
    "failureValue": 1500,
    "direction": "increasing",
    "drivers": ["master_battery"],
    "couples": [],
    "manifestsAs": ["position_light_white_out"],
    "inspectionMethod": "Visual check during preflight; test during night flight",
    "tboRelevance": "primary",
    "notes": "Filament lamp 1000 h MTBF; critical for night ops visibility."
  },
  {
    "id": "strobe_xenon_tube_flash_count_left",
    "system": "lighting",
    "subsystem": "Strobe Light",
    "displayName": "Strobe Xenon Tube Flash Count (Left)",
    "anpTerm": "Strobe Light Xenon Tube Flash Count Left",
    "unit": "flash_cycles",
    "nominalNew": 0,
    "serviceLimit": 20000000,
    "failureValue": 30000000,
    "direction": "increasing",
    "drivers": ["master_battery"],
    "couples": [],
    "manifestsAs": ["strobe_left_out"],
    "inspectionMethod": "Visual check in dim light; electrical test for tube voltage",
    "tboRelevance": "primary",
    "notes": "Xenon tube rated 30 million flashes (~5000 h at 1 Hz duty)."
  },
  {
    "id": "strobe_xenon_tube_flash_count_right",
    "system": "lighting",
    "subsystem": "Strobe Light",
    "displayName": "Strobe Xenon Tube Flash Count (Right)",
    "anpTerm": "Strobe Light Xenon Tube Flash Count Right",
    "unit": "flash_cycles",
    "nominalNew": 0,
    "serviceLimit": 20000000,
    "failureValue": 30000000,
    "direction": "increasing",
    "drivers": ["master_battery"],
    "couples": [],
    "manifestsAs": ["strobe_right_out"],
    "inspectionMethod": "Visual check in dim light; electrical test for tube voltage",
    "tboRelevance": "primary",
    "notes": "Xenon tube rated 30 million flashes (~5000 h at 1 Hz duty)."
  },
  {
    "id": "strobe_psu_capacitor_esr",
    "system": "lighting",
    "subsystem": "Strobe Power Supply",
    "displayName": "Strobe Power Supply Capacitor ESR",
    "anpTerm": "Strobe PSU High-Voltage Capacitor ESR",
    "unit": "ratio",
    "nominalNew": 0.05,
    "serviceLimit": 0.15,
    "failureValue": 0.25,
    "direction": "increasing",
    "drivers": ["master_battery", "ambient_temp_c"],
    "couples": ["strobe_xenon_tube_flash_count_left", "strobe_xenon_tube_flash_count_right"],
    "manifestsAs": ["strobe_dim", "strobe_power_supply_fail"],
    "inspectionMethod": "ESR meter test of reservoir capacitor; functional strobe timing check",
    "tboRelevance": "secondary",
    "notes": "Rising ESR degrades pulse energy and flash brightness; thermal cycling accelerates drift."
  },
  {
    "id": "beacon_led_driver_hours_modern",
    "system": "lighting",
    "subsystem": "Beacon Light",
    "displayName": "Beacon LED Driver Hours (Modern)",
    "anpTerm": "Beacon Light LED Driver Operating Hours",
    "unit": "hours",
    "nominalNew": 0,
    "serviceLimit": 50000,
    "failureValue": 80000,
    "direction": "increasing",
    "drivers": ["master_battery"],
    "couples": [],
    "manifestsAs": ["beacon_light_dim", "beacon_light_out"],
    "inspectionMethod": "Visual brightness check during daylight preflight; night test for red glow",
    "tboRelevance": "primary",
    "notes": "LED dims to 70% lumens at 50000 h; total failure by 80000 h."
  },
  {
    "id": "instrument_panel_post_light_dimming_pot_wear",
    "system": "lighting",
    "subsystem": "Panel Lighting",
    "displayName": "Instrument Panel Post-Light Dimming Pot Wear",
    "anpTerm": "Panel Light Rheostat Wiper Contact Wear",
    "unit": "ratio",
    "nominalNew": 0,
    "serviceLimit": 0.7,
    "failureValue": 0.95,
    "direction": "increasing",
    "drivers": ["master_battery"],
    "couples": [],
    "manifestsAs": ["panel_light_flicker", "panel_light_intermittent"],
    "inspectionMethod": "Rotate dimmer knob through full range; check for scratches/discontinuity",
    "tboRelevance": "secondary",
    "notes": "Repeated dimming cycles cause wiper wear; flicker indicates imminent pot failure."
  },
  {
    "id": "map_light_bulb_hours",
    "system": "lighting",
    "subsystem": "Map Light",
    "displayName": "Map Light Bulb Hours",
    "anpTerm": "Map Light Bulb Operating Hours",
    "unit": "hours",
    "nominalNew": 0,
    "serviceLimit": 1000,
    "failureValue": 1500,
    "direction": "increasing",
    "drivers": ["master_battery"],
    "couples": [],
    "manifestsAs": ["map_light_out"],
    "inspectionMethod": "Visual inspection; test switch in dark cabin",
    "tboRelevance": "incidental",
    "notes": "Standard incandescent 1000 h life; low criticality for ops."
  },
  {
    "id": "dome_light_bulb_hours",
    "system": "lighting",
    "subsystem": "Interior Lights",
    "displayName": "Dome Light Bulb Hours",
    "anpTerm": "Dome Light Bulb Operating Hours",
    "unit": "hours",
    "nominalNew": 0,
    "serviceLimit": 1000,
    "failureValue": 1500,
    "direction": "increasing",
    "drivers": ["master_battery"],
    "couples": [],
    "manifestsAs": ["dome_light_out"],
    "inspectionMethod": "Visual inspection; test overhead switch",
    "tboRelevance": "incidental",
    "notes": "Standard incandescent bulb; used for cabin illumination during preflight."
  },
  {
    "id": "glareshield_flood_light_hours",
    "system": "lighting",
    "subsystem": "Panel Lighting",
    "displayName": "Glareshield Flood Light Hours",
    "anpTerm": "Glareshield Flood Light Bulb Operating Hours",
    "unit": "hours",
    "nominalNew": 0,
    "serviceLimit": 1000,
    "failureValue": 1500,
    "direction": "increasing",
    "drivers": ["master_battery"],
    "couples": [],
    "manifestsAs": ["glareshield_light_out"],
    "inspectionMethod": "Visual check at night; inspect bulb socket for corrosion",
    "tboRelevance": "secondary",
    "notes": "Filament lamp providing general cockpit ambient light during night ops."
  },
  {
    "id": "fuel_sump_drain_inspection_light_hours",
    "system": "lighting",
    "subsystem": "Utility Lighting",
    "displayName": "Fuel Sump Drain Inspection Light Hours",
    "anpTerm": "Fuel Sump Inspection Light Bulb Operating Hours",
    "unit": "hours",
    "nominalNew": 0,
    "serviceLimit": 1000,
    "failureValue": 1500,
    "direction": "increasing",
    "drivers": ["master_battery"],
    "couples": [],
    "manifestsAs": ["sump_light_out"],
    "inspectionMethod": "Test with master on during preflight fuel sumping",
    "tboRelevance": "secondary",
    "notes": "Optional feature on some C172 models; aids fuel contamination inspection."
  },
  {
    "id": "pitot_heat_element_resistance",
    "system": "pitot_static",
    "subsystem": "Pitot Heat",
    "displayName": "Pitot Heat Element Resistance",
    "anpTerm": "Pitot Tube Heating Element DC Resistance",
    "unit": "ohms",
    "nominalNew": 3.2,
    "serviceLimit": 3.5,
    "failureValue": 999,
    "direction": "increasing",
    "drivers": ["ambient_temp_c", "engine_start"],
    "couples": ["pitot_mast_water_drain_hole_patency"],
    "manifestsAs": ["pitot_heat_inop", "pitot_system_iced"],
    "inspectionMethod": "Ohmmeter test of pitot heat element with power off; functional test during flight",
    "tboRelevance": "primary",
    "notes": "Open-circuit (>100 Ω) or short (<1 Ω) triggers failure; thermal cycling causes drift."
  },
  {
    "id": "pitot_mast_water_drain_hole_patency",
    "system": "pitot_static",
    "subsystem": "Pitot Mast",
    "displayName": "Pitot Mast Water-Drain Hole Patency",
    "anpTerm": "Pitot Mast Drain Port Blockage Status",
    "unit": "ratio",
    "nominalNew": 1.0,
    "serviceLimit": 0.8,
    "failureValue": 0.3,
    "direction": "decreasing",
    "drivers": ["parked_outdoors", "parked_outdoors_24h"],
    "couples": ["pitot_line_internal_moisture"],
    "manifestsAs": ["pitot_system_iced", "pitot_system_unreliable"],
    "inspectionMethod": "Visual inspection with borescope; test drain flow with compressed air",
    "tboRelevance": "primary",
    "notes": "Blockage from ice, dirt, or corrosion allows water trap formation in pitot line."
  },
  {
    "id": "pitot_line_internal_moisture",
    "system": "pitot_static",
    "subsystem": "Pitot System",
    "displayName": "Pitot Line Internal Moisture",
    "anpTerm": "Pitot Tubing Condensation Water Content",
    "unit": "ppm_co",
    "nominalNew": 0,
    "serviceLimit": 100,
    "failureValue": 500,
    "direction": "increasing",
    "drivers": ["cold_start", "ambient_temp_c"],
    "couples": ["pitot_heat_element_resistance", "pitot_mast_water_drain_hole_patency"],
    "manifestsAs": ["pitot_system_iced", "airspeed_indicator_erratic"],
    "inspectionMethod": "Moisture trap inspection; borescope exam of internal tubing for visible droplets",
    "tboRelevance": "primary",
    "notes": "Water ingress from condensation or rain; freezes in flight causing IAS blockage."
  },
  {
    "id": "pitot_tube_ram_air_port_screen_contamination",
    "system": "pitot_static",
    "subsystem": "Pitot Probe",
    "displayName": "Pitot Tube Ram-Air Port Screen Contamination",
    "anpTerm": "Pitot Probe Forward Port Screen Blockage",
    "unit": "ratio",
    "nominalNew": 0,
    "serviceLimit": 0.3,
    "failureValue": 0.8,
    "direction": "increasing",
    "drivers": ["parked_outdoors"],
    "couples": [],
    "manifestsAs": ["airspeed_indicator_low_reading"],
    "inspectionMethod": "Visual inspection of probe head; gentle air flush if safe",
    "tboRelevance": "secondary",
    "notes": "Dirt, bugs, or ice accumulation reduces dynamic pressure sensing accuracy."
  },
  {
    "id": "static_port_flushness_paint_buildup",
    "system": "pitot_static",
    "subsystem": "Static Ports",
    "displayName": "Static Port Flushness (Paint Buildup)",
    "anpTerm": "Static Port Paint Layer Thickness",
    "unit": "inches",
    "nominalNew": 0,
    "serviceLimit": 0.015,
    "failureValue": 0.05,
    "direction": "increasing",
    "drivers": ["parked_outdoors", "parked_outdoors_24h"],
    "couples": ["static_port_left_side"],
    "manifestsAs": ["altimeter_error_high", "airspeed_indicator_error"],
    "inspectionMethod": "Visual inspection; scribe or thickness gauge at static port rim",
    "tboRelevance": "primary",
    "notes": "Paint buildup causes static pressure error; can trigger ATC altitude bust."
  },
  {
    "id": "static_port_left_side",
    "system": "pitot_static",
    "subsystem": "Static Ports",
    "displayName": "Static Port Left Side",
    "anpTerm": "Left Static Port Condition",
    "unit": "ratio",
    "nominalNew": 1.0,
    "serviceLimit": 0.8,
    "failureValue": 0.3,
    "direction": "decreasing",
    "drivers": ["parked_outdoors", "parked_outdoors_24h"],
    "couples": ["static_port_flushness_paint_buildup"],
    "manifestsAs": ["altimeter_error_high", "static_system_blocked"],
    "inspectionMethod": "Visual inspection for cracks, corrosion, or blockage; FAR 91.411 test",
    "tboRelevance": "primary",
    "notes": "Corrosion or contamination reduces patency; paired port design relies on both sides."
  },
  {
    "id": "static_line_internal_moisture",
    "system": "pitot_static",
    "subsystem": "Static System",
    "displayName": "Static Line Internal Moisture",
    "anpTerm": "Static Tubing Condensation Water Content",
    "unit": "ppm_co",
    "nominalNew": 0,
    "serviceLimit": 150,
    "failureValue": 600,
    "direction": "increasing",
    "drivers": ["cold_start", "ambient_temp_c"],
    "couples": [],
    "manifestsAs": ["altimeter_erratic", "vertical_speed_indicator_sluggish"],
    "inspectionMethod": "Moisture trap inspection; visual check for water beads in tubing",
    "tboRelevance": "secondary",
    "notes": "Water condenses in static line during climb/descent transitions; freezes in icing."
  },
  {
    "id": "static_system_overall_leak_rate",
    "system": "pitot_static",
    "subsystem": "Static System",
    "displayName": "Static System Overall Leak Rate",
    "anpTerm": "Static System FAR 91.411 Leak Test Rate",
    "unit": "ft_per_min_leak",
    "nominalNew": 0,
    "serviceLimit": 75,
    "failureValue": 100,
    "direction": "increasing",
    "drivers": [],
    "couples": [],
    "manifestsAs": ["altimeter_unserviceable", "vertical_speed_indicator_unserviceable"],
    "inspectionMethod": "FAR 91.411 static system test; measure altitude loss at 1000 ft test altitude",
    "tboRelevance": "primary",
    "notes": "FAR 91.411 limit 100 ft/min at 1000 ft test alt; advisory 75 ft/min."
  },
  {
    "id": "alternate_static_valve_seat",
    "system": "pitot_static",
    "subsystem": "Static System",
    "displayName": "Alternate Static Valve Seat",
    "anpTerm": "Alternate Static Port Selector Valve Seat Sealing",
    "unit": "ratio",
    "nominalNew": 1.0,
    "serviceLimit": 0.85,
    "failureValue": 0.4,
    "direction": "decreasing",
    "drivers": [],
    "couples": [],
    "manifestsAs": ["static_system_leak", "altimeter_erratic"],
    "inspectionMethod": "Manual valve actuation test; pressure hold check with plug",
    "tboRelevance": "secondary",
    "notes": "Valve seat corrosion or debris allows leakage when closed; affects FAR 91.411 test."
  },
  {
    "id": "altitude_encoder_altitude_correlation_drift",
    "system": "pitot_static",
    "subsystem": "Altitude Encoder",
    "displayName": "Altitude Encoder Altitude Correlation Drift",
    "anpTerm": "Altitude Encoder Pressure-to-Altitude Conversion Accuracy",
    "unit": "feet",
    "nominalNew": 0,
    "serviceLimit": 50,
    "failureValue": 200,
    "direction": "increasing",
    "drivers": ["ambient_pressure"],
    "couples": [],
    "manifestsAs": ["altimeter_error", "encoder_unserviceable"],
    "inspectionMethod": "Functional altitude test against certified altimeter at known altitude",
    "tboRelevance": "primary",
    "notes": "Mode C altitude reporting requires ±100 ft accuracy; encoder drift causes ADS-B errors."
  },
  {
    "id": "vacuum_pump_vane_1_wear",
    "system": "vacuum",
    "subsystem": "Vacuum Pump",
    "displayName": "Vacuum Pump Vane #1 Wear",
    "anpTerm": "Vacuum Pump Rotor Vane 1 Thickness",
    "unit": "inches",
    "nominalNew": 0.55,
    "serviceLimit": 0.45,
    "failureValue": 0.35,
    "direction": "decreasing",
    "drivers": ["engine_rpm"],
    "couples": ["vacuum_pump_vane_2_wear", "vacuum_pump_vane_3_wear", "vacuum_pump_vane_4_wear"],
    "manifestsAs": ["suction_loss", "vacuum_pump_worn_out"],
    "inspectionMethod": "Pump teardown; measure vane thickness with calipers",
    "tboRelevance": "primary",
    "notes": "Scrap limit 0.40 in; all four vanes must meet limit together. G1000 NXi may not use vacuum."
  },
  {
    "id": "vacuum_pump_vane_2_wear",
    "system": "vacuum",
    "subsystem": "Vacuum Pump",
    "displayName": "Vacuum Pump Vane #2 Wear",
    "anpTerm": "Vacuum Pump Rotor Vane 2 Thickness",
    "unit": "inches",
    "nominalNew": 0.55,
    "serviceLimit": 0.45,
    "failureValue": 0.35,
    "direction": "decreasing",
    "drivers": ["engine_rpm"],
    "couples": ["vacuum_pump_vane_1_wear", "vacuum_pump_vane_3_wear", "vacuum_pump_vane_4_wear"],
    "manifestsAs": ["suction_loss", "vacuum_pump_worn_out"],
    "inspectionMethod": "Pump teardown; measure vane thickness with calipers",
    "tboRelevance": "primary",
    "notes": "Scrap limit 0.40 in; all four vanes must meet limit together. G1000 NXi may not use vacuum."
  },
  {
    "id": "vacuum_pump_vane_3_wear",
    "system": "vacuum",
    "subsystem": "Vacuum Pump",
    "displayName": "Vacuum Pump Vane #3 Wear",
    "anpTerm": "Vacuum Pump Rotor Vane 3 Thickness",
    "unit": "inches",
    "nominalNew": 0.55,
    "serviceLimit": 0.45,
    "failureValue": 0.35,
    "direction": "decreasing",
    "drivers": ["engine_rpm"],
    "couples": ["vacuum_pump_vane_1_wear", "vacuum_pump_vane_2_wear", "vacuum_pump_vane_4_wear"],
    "manifestsAs": ["suction_loss", "vacuum_pump_worn_out"],
    "inspectionMethod": "Pump teardown; measure vane thickness with calipers",
    "tboRelevance": "primary",
    "notes": "Scrap limit 0.40 in; all four vanes must meet limit together. G1000 NXi may not use vacuum."
  },
  {
    "id": "vacuum_pump_vane_4_wear",
    "system": "vacuum",
    "subsystem": "Vacuum Pump",
    "displayName": "Vacuum Pump Vane #4 Wear",
    "anpTerm": "Vacuum Pump Rotor Vane 4 Thickness",
    "unit": "inches",
    "nominalNew": 0.55,
    "serviceLimit": 0.45,
    "failureValue": 0.35,
    "direction": "decreasing",
    "drivers": ["engine_rpm"],
    "couples": ["vacuum_pump_vane_1_wear", "vacuum_pump_vane_2_wear", "vacuum_pump_vane_3_wear"],
    "manifestsAs": ["suction_loss", "vacuum_pump_worn_out"],
    "inspectionMethod": "Pump teardown; measure vane thickness with calipers",
    "tboRelevance": "primary",
    "notes": "Scrap limit 0.40 in; all four vanes must meet limit together. G1000 NXi may not use vacuum."
  },
  {
    "id": "vacuum_pump_shear_coupling",
    "system": "vacuum",
    "subsystem": "Vacuum Pump",
    "displayName": "Vacuum Pump Shear Coupling",
    "anpTerm": "Vacuum Pump Shear Coupling Pin Condition",
    "unit": "ratio",
    "nominalNew": 1.0,
    "serviceLimit": 0.7,
    "failureValue": 0,
    "direction": "decreasing",
    "drivers": [],
    "couples": [],
    "manifestsAs": ["vacuum_pump_drive_disconnect"],
    "inspectionMethod": "Visual inspection of coupling pin; functional test of pump operation",
    "tboRelevance": "primary",
    "notes": "Safety coupling shears if pump jams to protect engine drive; replacement required if sheared."
  },
  {
    "id": "suction_relief_valve_setpoint_drift",
    "system": "vacuum",
    "subsystem": "Vacuum Regulation",
    "displayName": "Suction Relief Valve Setpoint Drift",
    "anpTerm": "Vacuum System Relief Valve Setpoint Accuracy",
    "unit": "inches",
    "nominalNew": 5.0,
    "serviceLimit": 5.2,
    "failureValue": 6.5,
    "direction": "increasing",
    "drivers": ["ambient_pressure"],
    "couples": [],
    "manifestsAs": ["suction_overpressure", "vacuum_system_unserviceable"],
    "inspectionMethod": "Functional suction test at sea level; measure and compare to gauge",
    "tboRelevance": "primary",
    "notes": "Setpoint ±0.2 in Hg nominal (4.8–5.2 in Hg); exceeding 5.2 in Hg can cause pump failure."
  },
  {
    "id": "vacuum_filter_loading",
    "system": "vacuum",
    "subsystem": "Vacuum System",
    "displayName": "Vacuum Filter Loading",
    "anpTerm": "Vacuum Pump Inlet Filter Pressure Drop",
    "unit": "inches",
    "nominalNew": 0,
    "serviceLimit": 1.0,
    "failureValue": 1.5,
    "direction": "increasing",
    "drivers": ["engine_rpm"],
    "couples": [],
    "manifestsAs": ["suction_loss", "vacuum_filter_clogged"],
    "inspectionMethod": "Visual inspection of filter element; measure suction delta-P across filter",
    "tboRelevance": "secondary",
    "notes": "Replace filter when delta-P reaches 1.5 in Hg to maintain minimum system suction."
  },
  {
    "id": "vacuum_hose_internal_collapse",
    "system": "vacuum",
    "subsystem": "Vacuum Distribution",
    "displayName": "Vacuum Hose Internal Collapse",
    "anpTerm": "Vacuum System Hose Internal Wall Degradation",
    "unit": "ratio",
    "nominalNew": 1.0,
    "serviceLimit": 0.7,
    "failureValue": 0.2,
    "direction": "decreasing",
    "drivers": ["parked_outdoors", "ambient_temp_c"],
    "couples": [],
    "manifestsAs": ["suction_loss", "vacuum_hose_restriction"],
    "inspectionMethod": "Hose inspection with borescope; apply vacuum and check for collapse",
    "tboRelevance": "secondary",
    "notes": "Rubber aging and ozone exposure cause internal wall flaking; visual exterior check insufficient."
  },
  {
    "id": "suction_gauge_calibration_drift",
    "system": "vacuum",
    "subsystem": "Vacuum Instrumentation",
    "displayName": "Suction Gauge Calibration Drift",
    "anpTerm": "Vacuum System Pressure Gauge Accuracy",
    "unit": "inches",
    "nominalNew": 0,
    "serviceLimit": 0.3,
    "failureValue": 1.0,
    "direction": "increasing",
    "drivers": [],
    "couples": [],
    "manifestsAs": ["suction_gauge_unserviceable"],
    "inspectionMethod": "Functional test against calibrated test gauge at known suction setting",
    "tboRelevance": "secondary",
    "notes": "Mechanical gauge pointer stiction or mechanical hysteresis causes drift; 24-month certification required."
  },
  {
    "id": "cabin_heat_scat_tube_degradation",
    "system": "environmental",
    "subsystem": "Cabin Heat",
    "displayName": "Cabin Heat Scat Tube Degradation",
    "anpTerm": "Cabin Heat Scat Tube Visual Condition Score",
    "unit": "ratio",
    "nominalNew": 10,
    "serviceLimit": 6,
    "failureValue": 3,
    "direction": "decreasing",
    "drivers": ["ambient_temp_c", "parked_outdoors_24h"],
    "couples": ["cabin_heat_scat_tube_co_leak_risk"],
    "manifestsAs": ["cabin_heat_scat_tube_degraded"],
    "inspectionMethod": "Visual inspection of scat tube exterior; check for cracks, rust, or separation",
    "tboRelevance": "primary",
    "notes": "Condition score 10 (new) to 0 (failed); replace at score 4 to prevent CO ingress."
  },
  {
    "id": "cabin_heat_scat_tube_co_leak_risk",
    "system": "environmental",
    "subsystem": "Cabin Heat",
    "displayName": "Cabin Heat Scat Tube CO Leak Risk",
    "anpTerm": "Cabin Heat System Carbon Monoxide Ingress Probability",
    "unit": "ratio",
    "nominalNew": 0,
    "serviceLimit": 0.15,
    "failureValue": 0.6,
    "direction": "increasing",
    "drivers": ["ambient_temp_c"],
    "couples": ["cabin_heat_scat_tube_degradation"],
    "manifestsAs": ["co_contamination_risk"],
    "inspectionMethod": "Sealing check with soapy water; CO detector response during engine run",
    "tboRelevance": "primary",
    "notes": "Cracked scat tube allows combustion exhaust gases to enter cabin; critical safety issue."
  },
  {
    "id": "cabin_heat_valve_actuator_cable",
    "system": "environmental",
    "subsystem": "Cabin Heat",
    "displayName": "Cabin Heat Valve Actuator Cable",
    "anpTerm": "Cabin Heat Control Cable Tension and Travel",
    "unit": "ratio",
    "nominalNew": 1.0,
    "serviceLimit": 0.85,
    "failureValue": 0.3,
    "direction": "decreasing",
    "drivers": [],
    "couples": [],
    "manifestsAs": ["cabin_heat_control_sluggish", "cabin_heat_valve_stuck"],
    "inspectionMethod": "Visual inspection of cable routing; test cabin heat control lever full travel",
    "tboRelevance": "secondary",
    "notes": "Cable stretching or corrosion reduces actuator response; frayed cable requires replacement."
  },
  {
    "id": "defrost_valve_seat",
    "system": "environmental",
    "subsystem": "Defrost System",
    "displayName": "Defrost Valve Seat",
    "anpTerm": "Windscreen Defrost Valve Seat Sealing",
    "unit": "ratio",
    "nominalNew": 1.0,
    "serviceLimit": 0.8,
    "failureValue": 0.3,
    "direction": "decreasing",
    "drivers": [],
    "couples": [],
    "manifestsAs": ["defrost_system_ineffective", "hot_air_always_on"],
    "inspectionMethod": "Manual valve test; check for unwanted hot air discharge when valve closed",
    "tboRelevance": "secondary",
    "notes": "Valve seat corrosion or debris allows bypass leakage; impacts defrost effectiveness."
  },
  {
    "id": "fresh_air_vent_screen_contamination_left",
    "system": "environmental",
    "subsystem": "Fresh Air System",
    "displayName": "Fresh Air Vent Screen Contamination (Left)",
    "anpTerm": "Left Fresh Air Vent Screen Debris Loading",
    "unit": "ratio",
    "nominalNew": 0,
    "serviceLimit": 0.4,
    "failureValue": 0.85,
    "direction": "increasing",
    "drivers": ["parked_outdoors"],
    "couples": ["fresh_air_vent_screen_contamination_right"],
    "manifestsAs": ["fresh_air_flow_reduced"],
    "inspectionMethod": "Visual inspection of external vent screen; test fresh air control lever operation",
    "tboRelevance": "secondary",
    "notes": "Dirt, lint, or insects block vent screen reducing cabin fresh air flow."
  },
  {
    "id": "fresh_air_vent_screen_contamination_right",
    "system": "environmental",
    "subsystem": "Fresh Air System",
    "displayName": "Fresh Air Vent Screen Contamination (Right)",
    "anpTerm": "Right Fresh Air Vent Screen Debris Loading",
    "unit": "ratio",
    "nominalNew": 0,
    "serviceLimit": 0.4,
    "failureValue": 0.85,
    "direction": "increasing",
    "drivers": ["parked_outdoors"],
    "couples": ["fresh_air_vent_screen_contamination_left"],
    "manifestsAs": ["fresh_air_flow_reduced"],
    "inspectionMethod": "Visual inspection of external vent screen; test fresh air control lever operation",
    "tboRelevance": "secondary",
    "notes": "Dirt, lint, or insects block vent screen reducing cabin fresh air flow."
  },
  {
    "id": "oat_probe_drift",
    "system": "environmental",
    "subsystem": "OAT System",
    "displayName": "OAT Probe Drift",
    "anpTerm": "Outside Air Temperature Probe Accuracy",
    "unit": "degrees_C",
    "nominalNew": 0,
    "serviceLimit": 2,
    "failureValue": 5,
    "direction": "increasing",
    "drivers": ["ambient_temp_c"],
    "couples": [],
    "manifestsAs": ["oat_gauge_unreliable", "density_altitude_error"],
    "inspectionMethod": "Temperature comparison against calibrated reference at cruise altitude",
    "tboRelevance": "secondary",
    "notes": "OAT errors affect density altitude calculation and engine leaning decisions; ±2°C new, replace at ±5°C."
  },
  {
    "id": "carbon_monoxide_detector_electrochemical_cell_life",
    "system": "environmental",
    "subsystem": "CO Detection",
    "displayName": "Carbon Monoxide Detector Electrochemical Cell Life",
    "anpTerm": "CO Detector Electrochemical Cell Operating Hours",
    "unit": "years",
    "nominalNew": 2,
    "serviceLimit": 1.5,
    "failureValue": 0,
    "direction": "decreasing",
    "drivers": [],
    "couples": [],
    "manifestsAs": ["co_detector_expired", "co_detector_insensitive"],
    "inspectionMethod": "Check cell expiration date; test detector response to known CO source",
    "tboRelevance": "primary",
    "notes": "Electrochemical cell life 2 years regardless of use; expired cells fail to detect CO."
  },
  {
    "id": "carbon_monoxide_detector_battery",
    "system": "environmental",
    "subsystem": "CO Detection",
    "displayName": "Carbon Monoxide Detector Battery",
    "anpTerm": "CO Detector Battery Voltage and Capacity",
    "unit": "ratio",
    "nominalNew": 1.0,
    "serviceLimit": 0.8,
    "failureValue": 0.3,
    "direction": "decreasing",
    "drivers": [],
    "couples": [],
    "manifestsAs": ["co_detector_powered_down"],
    "inspectionMethod": "Battery voltage check; observe warning LED if equipped",
    "tboRelevance": "secondary",
    "notes": "Some CO detectors powered separately; check battery during annual inspection."
  },
  {
    "id": "com1_antenna_base_seal",
    "system": "antennas",
    "subsystem": "COM1 Antenna",
    "displayName": "COM1 Antenna Base Seal",
    "anpTerm": "COM1 Antenna Fuselage Penetration Seal Integrity",
    "unit": "ratio",
    "nominalNew": 1.0,
    "serviceLimit": 0.8,
    "failureValue": 0.2,
    "direction": "decreasing",
    "drivers": ["parked_outdoors", "ambient_temp_c"],
    "couples": [],
    "manifestsAs": ["com1_antenna_water_ingress"],
    "inspectionMethod": "Visual inspection of antenna base; check for water staining or corrosion",
    "tboRelevance": "secondary",
    "notes": "Sealant degradation allows water ingress to antenna connector; causes intermittent TX/RX."
  },
  {
    "id": "com2_antenna_base_seal",
    "system": "antennas",
    "subsystem": "COM2 Antenna",
    "displayName": "COM2 Antenna Base Seal",
    "anpTerm": "COM2 Antenna Fuselage Penetration Seal Integrity",
    "unit": "ratio",
    "nominalNew": 1.0,
    "serviceLimit": 0.8,
    "failureValue": 0.2,
    "direction": "decreasing",
    "drivers": ["parked_outdoors", "ambient_temp_c"],
    "couples": [],
    "manifestsAs": ["com2_antenna_water_ingress"],
    "inspectionMethod": "Visual inspection of antenna base; check for water staining or corrosion",
    "tboRelevance": "secondary",
    "notes": "Sealant degradation allows water ingress to antenna connector; causes intermittent TX/RX."
  },
  {
    "id": "gps_antenna_seal_and_element_gain",
    "system": "antennas",
    "subsystem": "GPS Antenna",
    "displayName": "GPS Antenna Seal and Element Gain",
    "anpTerm": "GPS Antenna Radome Seal and Element Radiation Pattern",
    "unit": "VSWR",
    "nominalNew": 1.2,
    "serviceLimit": 1.5,
    "failureValue": 3.0,
    "direction": "increasing",
    "drivers": ["parked_outdoors", "ambient_temp_c"],
    "couples": [],
    "manifestsAs": ["gps_signal_acquisition_slow", "gps_position_error"],
    "inspectionMethod": "Visual radome inspection; measure antenna VSWR with vector analyzer if available",
    "tboRelevance": "secondary",
    "notes": "Radome water ingress increases VSWR and reduces gain; impacts precision approach capability."
  },
  {
    "id": "transponder_antenna_ground_plane_corrosion",
    "system": "antennas",
    "subsystem": "Transponder Antenna",
    "displayName": "Transponder Antenna Ground Plane Corrosion",
    "anpTerm": "Mode C Antenna Ground Plane Surface Condition",
    "unit": "ratio",
    "nominalNew": 1.0,
    "serviceLimit": 0.8,
    "failureValue": 0.3,
    "direction": "decreasing",
    "drivers": ["parked_outdoors", "ambient_temp_c"],
    "couples": [],
    "manifestsAs": ["transponder_altitude_error", "mode_c_altitude_reporting_error"],
    "inspectionMethod": "Visual inspection of fuselage ground plane around antenna; check for rust or corrosion",
    "tboRelevance": "primary",
    "notes": "Corroded ground plane causes VSWR mismatch and altitude encoding errors in ADS-B reports."
  },
  {
    "id": "adsb_uat_antenna_seal",
    "system": "antennas",
    "subsystem": "ADS-B/UAT Antenna",
    "displayName": "ADS-B/UAT Antenna Seal",
    "anpTerm": "ADS-B Antenna Radome Seal Integrity",
    "unit": "ratio",
    "nominalNew": 1.0,
    "serviceLimit": 0.8,
    "failureValue": 0.2,
    "direction": "decreasing",
    "drivers": ["parked_outdoors", "ambient_temp_c"],
    "couples": [],
    "manifestsAs": ["adsb_uat_signal_loss"],
    "inspectionMethod": "Visual radome inspection; check for moisture or separation",
    "tboRelevance": "secondary",
    "notes": "Radome seal failure allows water intrusion affecting antenna impedance matching."
  },
  {
    "id": "elt_antenna_whip_flexibility",
    "system": "antennas",
    "subsystem": "ELT Antenna",
    "displayName": "ELT Antenna Whip Flexibility",
    "anpTerm": "Emergency Locator Transmitter Antenna Structural Integrity",
    "unit": "ratio",
    "nominalNew": 1.0,
    "serviceLimit": 0.7,
    "failureValue": 0.1,
    "direction": "decreasing",
    "drivers": ["parked_outdoors", "ambient_temp_c"],
    "couples": [],
    "manifestsAs": ["elt_antenna_fractured"],
    "inspectionMethod": "Visual inspection; gently flex antenna to check for cracks or brittleness",
    "tboRelevance": "primary",
    "notes": "ELT antenna whip embrittles from UV and cold; broken antenna impairs emergency signal transmission."
  },
  {
    "id": "dme_antenna_condition",
    "system": "antennas",
    "subsystem": "DME Antenna",
    "displayName": "DME Antenna Condition",
    "anpTerm": "Distance Measuring Equipment Antenna Element Condition",
    "unit": "ratio",
    "nominalNew": 1.0,
    "serviceLimit": 0.8,
    "failureValue": 0.2,
    "direction": "decreasing",
    "drivers": ["parked_outdoors", "ambient_temp_c"],
    "couples": [],
    "manifestsAs": ["dme_signal_loss", "dme_distance_error"],
    "inspectionMethod": "Visual antenna inspection; functional DME range test from known station",
    "tboRelevance": "secondary",
    "notes": "Optional equipment on some C172 models; antenna corrosion degrades DME acquisition range."
  },
  {
    "id": "master_caution_lamp_hours",
    "system": "annunciators",
    "subsystem": "Master Caution",
    "displayName": "Master Caution Lamp Hours",
    "anpTerm": "Master Caution Annunciator Bulb Operating Hours",
    "unit": "hours",
    "nominalNew": 0,
    "serviceLimit": 1000,
    "failureValue": 1500,
    "direction": "increasing",
    "drivers": ["master_battery"],
    "couples": [],
    "manifestsAs": ["master_caution_lamp_out"],
    "inspectionMethod": "Visual check; test lamp during preflight by actuating test switch",
    "tboRelevance": "secondary",
    "notes": "Filament lamp 1000 h life; failure obscures caution panel alerting function."
  },
  {
    "id": "low_voltage_annunciator_threshold_drift",
    "system": "annunciators",
    "subsystem": "Low Voltage Alert",
    "displayName": "Low Voltage Annunciator Threshold Drift",
    "anpTerm": "Low Bus Voltage Alert Threshold Accuracy",
    "unit": "ratio",
    "nominalNew": 0,
    "serviceLimit": 0.05,
    "failureValue": 0.15,
    "direction": "increasing",
    "drivers": ["bus_v"],
    "couples": [],
    "manifestsAs": ["low_voltage_alert_inaccurate"],
    "inspectionMethod": "Functional test with variable power supply; observe alert trigger point",
    "tboRelevance": "secondary",
    "notes": "Electronic threshold drift causes false alerts or delayed low-voltage warning."
  },
  {
    "id": "fuel_selector_position_switch_wear",
    "system": "annunciators",
    "subsystem": "Fuel Selector Indicator",
    "displayName": "Fuel Selector Position Switch Wear",
    "anpTerm": "Fuel Tank Selector Valve Position Switch Contact Wear",
    "unit": "ratio",
    "nominalNew": 1.0,
    "serviceLimit": 0.8,
    "failureValue": 0.3,
    "direction": "decreasing",
    "drivers": [],
    "couples": [],
    "manifestsAs": ["fuel_selector_position_indicator_erratic"],
    "inspectionMethod": "Rotate fuel selector through all positions; observe indicator panel lamp changes",
    "tboRelevance": "secondary",
    "notes": "Switch contact wear causes intermittent position indication; replacement required if unreliable."
  },
  {
    "id": "low_fuel_annunciator_threshold_drift",
    "system": "annunciators",
    "subsystem": "Low Fuel Alert",
    "displayName": "Low Fuel Annunciator Threshold Drift",
    "anpTerm": "Low Fuel Tank Level Alert Threshold Accuracy",
    "unit": "ratio",
    "nominalNew": 0,
    "serviceLimit": 0.08,
    "failureValue": 0.25,
    "direction": "increasing",
    "drivers": [],
    "couples": [],
    "manifestsAs": ["low_fuel_alert_inaccurate"],
    "inspectionMethod": "Functional fuel quantity test against float level; measure alert actuation point",
    "tboRelevance": "primary",
    "notes": "Drift causes false low-fuel warnings or delayed alert; critical for flight planning accuracy."
  },
  {
    "id": "starter_engaged_annunciator_condition",
    "system": "annunciators",
    "subsystem": "Starter Indicator",
    "displayName": "Starter Engaged Annunciator Condition",
    "anpTerm": "Starter Engaged Indicator Lamp Status",
    "unit": "ratio",
    "nominalNew": 1.0,
    "serviceLimit": 0.85,
    "failureValue": 0.2,
    "direction": "decreasing",
    "drivers": ["master_battery"],
    "couples": [],
    "manifestsAs": ["starter_indicator_inop"],
    "inspectionMethod": "Attempt engine start; observe indicator lamp illumination",
    "tboRelevance": "incidental",
    "notes": "Optional equipment on some C172 models; not present on all variants."
  }
]
